LICENSE
MANIFEST.in
README.md
entry-points.ini
requirements.txt
setup.py
pop_utils.egg-info/PKG-INFO
pop_utils.egg-info/SOURCES.txt
pop_utils.egg-info/dependency_links.txt
pop_utils.egg-info/entry_points.txt
pop_utils.egg-info/requires.txt
pop_utils.egg-info/top_level.txt
poputils/__init__.py
poputils/conf.py
poputils/xml.py
poputils/bin/__init__.py
poputils/bin/destroy.py
poputils/bin/master.py
poputils/bin/setup.py
poputils/boto/__init__.py
poputils/boto/ec2.py
poputils/boto/error.py
poputils/boto/vpc.py
poputils/fabfiles/__init__.py
poputils/fabfiles/common.py
poputils/fabfiles/local.pyt
poputils/fabfiles/manager.py
poputils/fabfiles/remote.py
poputils/schemata/cloud-instance.xsd
poputils/schemata/cloud-setup.xsd
poputils/schemata/master-image.xsd
poputils/utils/__init__.py
poputils/utils/cidr.py
poputils/utils/fabric.py
poputils/utils/shell.py