Metadata-Version: 1.0
Name: pop-utils
Version: 0.1
Summary: Collection of utilities to optimize the deployment and management of a POP-C++ or POP-Java based setup with a special focus on cloud deployments and Amazon Web Services.
Home-page: https://github.com/GaretJax/pop-utils
Author: Jonathan Stoppani
Author-email: jonathan.stoppani@gmail.com
License: MIT
Keywords: pop cloud utils aws eucalyptus
Platform: UNKNOWN
Classifier: Development Status :: 4 - Beta
Classifier: Environment :: Console
Classifier: Intended Audience :: Developers
Classifier: Intended Audience :: Education
Classifier: Intended Audience :: Information Technology
Classifier: Intended Audience :: Science/Research
Classifier: Intended Audience :: System Administrators
Classifier: License :: OSI Approved :: MIT License
Classifier: Operating System :: POSIX
Classifier: Topic :: System :: Distributed Computing
Classifier: Topic :: Utilities
